.gitignore
MANIFEST.in
README.rst
setup.py
pubmed2/__init__.py
pubmed2/info.py
pubmed2/pubmed.py
pubmed2.egg-info/PKG-INFO
pubmed2.egg-info/SOURCES.txt
pubmed2.egg-info/dependency_links.txt
pubmed2.egg-info/entry_points.txt
pubmed2.egg-info/requires.txt
pubmed2.egg-info/top_level.txt
pubmed2/templates/index.html
pubmed2/tools/__init__.py
pubmed2/tools/getIF.py
pubmed2/tools/impact_factor.sqlite3
pubmed2/tools/utils.py