Metadata-Version: 1.1
Name: pubmed2
Version: 0.0.7
Summary: search pubmeds quickly
Home-page: https://github.com/suqingdong/pubmed2
Author: suqingdong
Author-email: suqingdong@novogene.com
License: BSD License
Platform: UNKNOWN
Classifier: Development Status :: 5 - Production/Stable
Classifier: Operating System :: OS Independent
Classifier: Intended Audience :: Developers
Classifier: License :: OSI Approved :: BSD License
Classifier: Programming Language :: Python
Classifier: Programming Language :: Python :: Implementation
Classifier: Programming Language :: Python :: 2
Classifier: Programming Language :: Python :: 2.7
Classifier: Topic :: Software Development :: Libraries
